{"stats":{"total":46,"passed":46},"status":"passed","newTests":[{"id":"160ebc62207b43636131b01e38d61c5c","name":"Invalid Login with valid user and empty password","status":"passed","duration":839},{"id":"7793e64d212a36c834e44c3167f748bc","name":"Invalid Login with empty user and password","status":"passed","duration":765},{"id":"47e904c64072876ffca4b3ea821d471a","name":"Add FleeceJacket product and find price","status":"passed","duration":990},{"id":"b0f189e913110c770b7c8b5e542e53ab","name":"Complete Order and logout","status":"passed","duration":2791},{"id":"d96b929a19e25326d53ff43d6c4d5d60","name":"Fill Checkout Information","status":"passed","duration":1333},{"id":"dc3f72e2b6982234721564cae6ec1e1b","name":"Add All Products to Cart","status":"passed","duration":1251},{"id":"f05e1dabb0ebc40f202f82be7a0f9ffb","name":"Find Shipping Information","status":"passed","duration":1441},{"id":"f39bd78651fa50dbd9bd19bc72f9678c","name":"Navigate to LinkedIN Page","status":"passed","duration":3189},{"id":"00f0f8e41638b3140bdd1bfb453be665","name":"Add RedShirt product and find price","status":"passed","duration":1067},{"id":"9cb373cf0d09079803094eb1e5fc6ed4","name":"Invaild Login both username and password","status":"passed","duration":822},{"id":"30ab2e2f1ad28992b508d2f7bc6aa351","name":"Find Copy Rights Year","status":"passed","duration":687},{"id":"0663e9b98ce2d69c5fb5817166bf9269","name":"Add top 3 products to cart","status":"passed","duration":1209},{"id":"ed3abb28bd3d61074106aa59120d62ee","name":"Add All Products to Cart than remove them","status":"passed","duration":9921},{"id":"7604aebac398a45c90e3f0e1ba3c380c","name":"Add BikeLight product and find price","status":"passed","duration":889},{"id":"aa1e4c7f185b07e9c5cde3110b7002bf","name":"Find BikeLight Price","status":"passed","duration":1463},{"id":"5f9ec54a89ca5f10ac23383b5423a60b","name":"Find Onesie Price","status":"passed","duration":1497},{"id":"7c3923be3562a1093d6a17c0a83500b8","name":"Invalid Login with Locked User","status":"passed","duration":819},{"id":"b18798e70fff8d4a53eb17d78b6a0228","name":"Fill Checkout Information Without First Name","status":"passed","duration":1342},{"id":"fe83e91d820e7db77184dc26719a8e15","name":"Add All Products to Cart then remove some","status":"passed","duration":1556},{"id":"6c788e414e1b541b345cc382fa9c1f7e","name":"Find FleeceJacket Price","status":"passed","duration":1443},{"id":"3ae95866aac3ee24d0b821ace8037046","name":"Change Sorting Lowest to Highest","status":"passed","duration":994},{"id":"ddafad1abe21436ac579eadbb54fbc15","name":"Invalid Login with empty user only","status":"passed","duration":750},{"id":"8b0d4f4f96bac955c12d8e79223f563a","name":"Full End to End Scenario","status":"passed","duration":1507},{"id":"8a095b66fe3119fce1965abe75f154d6","name":"Navigate to Facebook Page","status":"passed","duration":2340},{"id":"1c0c4a372a1c04104fd715f5bcf254e9","name":"Add Onesie product and find price","status":"passed","duration":1023},{"id":"a013d5b84a32501de50a562db493d927","name":"Add Products and Open Cart Page","status":"passed","duration":1222},{"id":"a1c88ced89e45c213ddb4881c45dcaab","name":"Fill Checkout Information Without Second Name","status":"passed","duration":1252},{"id":"5ae6ebb70893ea6ddec0baacc17ebac2","name":"Add All Products to Cart than remove then add","status":"passed","duration":2300},{"id":"aec3fb5bdeed2e1942495b41bbc33e7e","name":"Find Payment Information","status":"passed","duration":1446},{"id":"a19dc97be4d3ff191e5de2c8f5416ad2","name":"Finish Order and Reorder again","status":"passed","duration":1892},{"id":"88a95d397a5bbaaa9a58dcd80bab25d2","name":"Invalid Login only Password","status":"passed","duration":788},{"id":"877afbed28ac3e33e863cb30afc6598e","name":"Click Back to Home","status":"passed","duration":1613},{"id":"92f178dd6895ef3cf369324d230e9eb5","name":"Add Backpack product and find price","status":"passed","duration":1077},{"id":"817adac0a14985af59126861c1c12e79","name":"Invalid Login only Username","status":"passed","duration":807},{"id":"d93a3d7f834430465725784dedcfc1c6","name":"Add BoltTShirt product and find price","status":"passed","duration":1017},{"id":"93d946cf017a14197f0cbb501bc4a533","name":"Find Backpack Price","status":"passed","duration":1436},{"id":"d20b46c8ab8c1d0a917ecf2f5e1c52e7","name":"Change Sorting Highest price to Lowest","status":"passed","duration":923},{"id":"7b2e525b381a8e4e4bc826845338e4ea","name":"Navigate to Twitter Page","status":"passed","duration":2159},{"id":"4a9288f259c1189a6e1c506d1d0fb21c","name":"Finish Order","status":"passed","duration":1731},{"id":"fca306ade008436d50d3a08bc8f464f0","name":"Add Products to cart then Logout","status":"passed","duration":2113},{"id":"72cdda7d3154b8c5235ce216e196dffa","name":"Add To Cart Then Logout","status":"passed","duration":1939},{"id":"be465dd0ed03f0ca04eb6f5994999f03","name":"Add All Products to Cart","status":"passed","duration":9866},{"id":"b6e7d469db61551e73c128597a2c2622","name":"Valid Login","status":"passed","duration":677},{"id":"b9890641ed2fe9ae0c95c174aea4e349","name":"Navigate to about page","status":"passed","duration":4476},{"id":"8ee930921ada9b9a6fb734b7fe696511","name":"Fill Checkout Information Without Zip Code","status":"passed","duration":1261},{"id":"7fe012c5d8a6008b9e97406a3fac6514","name":"Add lower 3 products to cart","status":"passed","duration":1193}],"flakyTests":[],"retryTests":[],"name":"Playwright Test Report","duration":83116,"createdAt":1779916168639,"plugin":"Awesome","meta":{"reportId":"b7c0bbd4-8de0-4034-8232-f3264475623b","singleFile":true,"withTestResultsLinks":true},"pluginId":"awesome","pullRequestHref":"","jobHref":"https://github.com/Ahmed2015-22/swag-labs-e2e-playwright/actions/runs/26538832368"}